{
  "status": "正常",
  "error": "",
  "updated_at": "2026-07-03 20:37:40",
  "data": {
    "timestamp": "2026-07-03 20:37:40",
    "strategies": {
      "獨贏一": {
        "url": "https://sports.icux.xyz/football/index1.php?t=21",
        "update_info": "更新59",
        "sections": [],
        "scraped_at": "20:37:41"
      },
      "獨贏二": {
        "url": "https://sports.icux.xyz/football/index1.php?t=6",
        "update_info": "更新59",
        "sections": [],
        "scraped_at": "20:37:43"
      },
      "大分二": {
        "url": "https://sports.icux.xyz/football/index3.php?t=2",
        "update_info": "更新59",
        "sections": [],
        "scraped_at": "20:37:45"
      },
      "大分三": {
        "url": "https://sports.icux.xyz/football/index3.php?t=3",
        "update_info": "更新59",
        "sections": [],
        "scraped_at": "20:37:47"
      },
      "策略一": {
        "url": "https://sports.icux.xyz/football/index5.php?t=6",
        "update_info": "更新59",
        "sections": [],
        "scraped_at": "20:37:48"
      },
      "策略二": {
        "url": "https://sports.icux.xyz/football/index5.php?t=2",
        "update_info": "更新59",
        "sections": [],
        "scraped_at": "20:37:50"
      },
      "策略四": {
        "url": "https://sports.icux.xyz/football/index7.php?t=0",
        "update_info": "更新59",
        "sections": [],
        "scraped_at": "20:37:52"
      },
      "策略五": {
        "url": "https://sports.icux.xyz/football/index7.php?t=2",
        "update_info": "更新59",
        "sections": [],
        "scraped_at": "20:37:53"
      },
      "隊伍三": {
        "url": "https://sports.icux.xyz/football/index7.php?t=4",
        "update_info": "更新59",
        "sections": [],
        "scraped_at": "20:37:55"
      },
      "數據一": {
        "url": "https://sports.icux.xyz/football/index9.php?t=0",
        "update_info": "更新59",
        "sections": [],
        "scraped_at": "20:37:57"
      },
      "數據二": {
        "url": "https://sports.icux.xyz/football/index9.php?t=2",
        "update_info": "更新59",
        "sections": [],
        "scraped_at": "20:37:59"
      },
      "數據三": {
        "url": "https://sports.icux.xyz/football/index9.php?t=4",
        "update_info": "更新59",
        "sections": [],
        "scraped_at": "20:38:00"
      }
    }
  }
}